{
	"name": "first-network",
	"version": "1.0.0",
	"client": {
		"tlsEnable": true,
		"adminCredential": {
			"id": "admin",
			"password": "adminpw"
		},
		"enableAuthentication": true,
		"organization": "org1",
		"connection": {
			"timeout": {
				"peer": {
					"endorser": "300"
				},
				"orderer": "300"
			}
		}
	},
	"channels": {
		"main": {
			"peers": {
				"peer0-org1": {},
				"peer1-org1": {},
				"peer0-org2": {},
				"peer1-org2": {}
			},
			"connection": {
				"timeout": {
					"peer": {
						"endorser": "6000",
						"eventHub": "6000",
						"eventReg": "6000"
					}
				}
			}
		}
	},
	"organizations": {
		"org1": {
			"mspid": "org1",
			"adminPrivateKey": {
				"path": "/tmp/crypto/peerOrganizations/org1/users/Admin@org1/msp/keystore/aa904a17aec65456b486be7da7aada45cd28889efc1d79c71a2788d9b42b1dee_sk"
			},
			"peers": ["peer0-org1","peer1-org1"],
			"signedCert": {
				"path": "/tmp/crypto/peerOrganizations/org1/users/Admin@org1/msp/signcerts/Admin@org1-cert.pem"
			}
		},
		"org2": {
			"mspid": "org2",
			"adminPrivateKey": {
				"path": "/tmp/crypto/peerOrganizations/org2/users/Admin@org2/msp/keystore/503d96810635600f7dd9f04e70357f80f4d0465fdf57623d0639270d1d9dc90d_sk"
			},
			"peers": ["peer0-org2","peer1-org2"],
			"signedCert": {
				"path": "/tmp/crypto/peerOrganizations/org2/users/Admin@org2/msp/signcerts/Admin@org2-cert.pem"
			}
		}
	},
	"peers": {
		"peer0-org1": {
			"tlsCACerts": {
				"path": "/tmp/crypto/peerOrganizations/org1/peers/peer0-org1/tls/ca.crt"
			},
			"url": "grpcs://peer0-org1:7051"
		},
		"peer1-org1": {
			"tlsCACerts": {
				"path": "/tmp/crypto/peerOrganizations/org1/peers/peer1-org1/tls/ca.crt"
			},
			"url": "grpcs://peer1-org1:8051"
		},
		"peer0-org2": {
			"tlsCACerts": {
				"path": "/tmp/crypto/peerOrganizations/org2/peers/peer0-org2/tls/ca.crt"
			},
			"url": "grpcs://peer0-org2:9051"
		},
		"peer1-org2": {
			"tlsCACerts": {
				"path": "/tmp/crypto/peerOrganizations/org2/peers/peer1-org2/tls/ca.crt"
			},
			"url": "grpcs://peer1-org2:10051"
		}
	}
}
